immature_zcm.py
Mature_jk-2.0.dist-info/METADATA
Mature_jk-2.0.dist-info/WHEEL
Mature_jk-2.0.dist-info/top_level.txt
Mature_jk-2.0.dist-info/RECORD
