Metadata-Version: 2.1
Name: Mature-jk
Version: 2.0
Summary: 张青mysql具体详情
Home-page: UNKNOWN
Author: 张青
Author-email: 3085058568@qq.com
License: UNKNOWN
Platform: UNKNOWN
